omniparse/__init__.py
omniparse/main.py
omniparse/prebuilt_agent.py
omniparse/utils.py
omniparse-0.0.3.dist-info/LICENSE
omniparse-0.0.3.dist-info/METADATA
omniparse-0.0.3.dist-info/WHEEL
omniparse-0.0.3.dist-info/RECORD
